{
    "Title": "The Partition of Omega6.1 into 24 parts",
    
    "Points": {
        "O": "(0, 0)",
        "A": "(-0.2886751346,-0.5)",
        "E": "(-0.2886751346, 0.5)",
        "W2": "(-0.4191751346, -0.2739673696)",
        "W3": "(-0.4191751346,  0.2739673696)",
        "T2": "(-0.3122332781, -0.2400653662)",
        "T3": "(-0.3122332781,  0.2400653662)",
        "X": "(-0.1581751346, -0.2739673696)",
        "X1": "(-0.1581751346, 0.2739673696)",
        "K": "(-0.0753442101, -0.1305)",
        "K1": "(-0.0753442101, 0.1305)",
        "H": "(-0.5, -0.1339745962)",
        "I": "(-0.5,  0.1339745962)",
        "N5": "(-0.5, -0.0587792438)",
        "N6": "(-0.5,  0.0587792438)",
        "U2": "(-0.3311075869, -0.0784798587)",
        "U3": "(-0.3311075869,  0.0784798587)",
        "S2": "(-0.2588825063, -0.0331790284)",
        "S3": "(-0.2588825063,  0.0331790284)",
        "W": "(-0.0276751346, -0.5)",
        "W4": "(-0.0276751346, 0.5)",
        "T": "(-0.0517860666, -0.3904346338)",
        "T4": "(-0.0517860666, 0.3904346338)",
        "U": "(0.0975882422, -0.325987511)",
        "Z3": "(0.0975882422, 0.325987511)",
        "Up": "(0.2335193447, -0.2475076523)",
        "Z2": "(0.2335193447,  0.2475076523)",
        "S": "(0.1007073717, -0.2407883412)",
        "S4": "(0.1007073717, 0.2407883412)",
        "Sp": "(0.1581751346, -0.2076093129)",
        "S1": "(0.1581751346,  0.2076093129)",
        "Tp": "(0.3640193447, -0.1503692677)",
        "T1": "(0.3640193447,  0.1503692677)",
        "M": "(0.1339745962, -0.5)",
        "M3": "(0.1339745962, 0.5)",
        "Mp": "(0.3660254038, -0.3660254038)",
        "M2": "(0.3660254038,  0.3660254038)",
        "N": "(0.1990956817, -0.4624023238)",
        "N3": "(0.1990956817, 0.4624023238)",
        "Np": "(0.3009043183, -0.40362308)",
        "N2": "(0.3009043183,  0.40362308)",
        "Wp": "(0.4468502692, -0.2260326304)",
        "W1": "(0.4468502692,  0.2260326304)",
        "Kp": "(0.1506884203, 0)",
        "Xp": "(0.3163502692, 0)",
        "C": "(0.5773502692, 0)"
    },

    "Omega": "('A', 'W', 'M', 'N', 'Np', 'Mp', 'Wp', 'C', 'W1', 'M2', 'N2', 'N3', 'M3', 'W4', 'E', 'W3', 'I', 'N6', 'N5', 'H', 'W2')",

    "Partition": [
        "('A', 'W', 'T', 'X')",
        "('W', 'M', 'N', 'U', 'T')",
        "('T', 'U', 'S', 'K', 'X')",
        "('N', 'Np', 'Up', 'Sp', 'S', 'U')",
        "('Np', 'Mp', 'Wp', 'Tp', 'Up')",
        "('O', 'K', 'S', 'Sp', 'Kp')",
        "('Kp', 'Sp', 'Up', 'Tp', 'Xp')",
        "('Wp', 'C', 'Xp', 'Tp')",
        "('O', 'Kp', 'S1', 'S4', 'K1')",
        "('Kp', 'Xp', 'T1', 'Z2', 'S1')",
        "('Xp', 'C', 'W1', 'T1')",
        "('T1', 'W1', 'M2', 'N2', 'Z2')",
        "('N2', 'N3', 'Z3', 'S4', 'S1', 'Z2')",
        "('N3', 'M3', 'W4', 'T4', 'Z3')",
        "('Z3', 'T4', 'X1', 'K1', 'S4')",
        "('W4', 'E', 'X1', 'T4')",
        "('O', 'K1', 'S3', 'S2', 'K')",
        "('K1', 'X1', 'T3', 'U3', 'S3')",
        "('K', 'S2', 'U2', 'T2', 'X')",
        "('X1', 'E', 'W3', 'T3')",
        "('W3', 'I', 'N6', 'U3', 'T3')",
        "('N6', 'N5', 'U2', 'S2', 'S3', 'U3')",
        "('N5', 'H', 'W2', 'T2', 'U2')",
        "('W2', 'A', 'X', 'T2')"
    ]
}